text_chatgpt_connector/__init__.py
text_chatgpt_connector/__version__.py
text_chatgpt_connector/main.py
text_chatgpt_connector/tcc.py
text_chatgpt_connector-0.0.2.dist-info/LICENSE
text_chatgpt_connector-0.0.2.dist-info/METADATA
text_chatgpt_connector-0.0.2.dist-info/WHEEL
text_chatgpt_connector-0.0.2.dist-info/entry_points.txt
text_chatgpt_connector-0.0.2.dist-info/RECORD
