Metadata-Version: 2.1
Name: text-chatgpt-connector
Version: 0.0.2
Summary: ChatGPT reads Text files
Home-page: https://github.com/rcmdnk/text_chatgpt_connector
License: MIT
Keywords: API,ChatGPT,AI
Author: rcmdnk
Author-email: rcmdnk@gmail.com
Requires-Python: >=3.8.1,<3.12
Classifier: License :: OSI Approved :: MIT License
Classifier: Programming Language :: Python :: 3
Classifier: Programming Language :: Python :: 3.9
Classifier: Programming Language :: Python :: 3.10
Classifier: Programming Language :: Python :: 3.11
Requires-Dist: numpy (>=1.24.2,<2.0.0)
Requires-Dist: openai (>=0.27.2,<0.28.0)
Requires-Dist: tiktoken (>=0.3.2,<0.4.0)
Project-URL: Repository, https://github.com/rcmdnk/text_chatgpt_connector
